.gitignore
LICENSE
Makefile
README.rst
setup.py
notebooks/ACS.ipynb
notebooks/Special Features of Census Dataframe.ipynb
publicdata/__init__.py
publicdata/appurl.py
publicdata/exc.py
publicdata/ffiec.py
publicdata/metapack.py
publicdata/util.py
publicdata.egg-info/PKG-INFO
publicdata.egg-info/SOURCES.txt
publicdata.egg-info/dependency_links.txt
publicdata.egg-info/entry_points.txt
publicdata.egg-info/requires.txt
publicdata.egg-info/top_level.txt
publicdata.egg-info/zip-safe
publicdata/bls/__init__.py
publicdata/bls/seriesid.py
publicdata/bls/test/__init__.py
publicdata/bls/test/test_basic.py
publicdata/census/__init__.py
publicdata/census/appurl.py
publicdata/census/bib.py
publicdata/census/dataframe.py
publicdata/census/dimensions.py
publicdata/census/exceptions.py
publicdata/census/func.py
publicdata/census/geocode.py
publicdata/census/groupby.py
publicdata/census/series.py
publicdata/census/util.py
publicdata/census/varrep.py
publicdata/census/api/__init__.py
publicdata/census/api/censusapi.py
publicdata/census/censusreporter/__init__.py
publicdata/census/censusreporter/exceptions.py
publicdata/census/censusreporter/generator.py
publicdata/census/censusreporter/jsonurl.py
publicdata/census/censusreporter/url.py
publicdata/census/censusreporter/test/__init__.py
publicdata/census/censusreporter/test/test_censusreporter.py
publicdata/census/files/__init__.py
publicdata/census/files/appurl.py
publicdata/census/files/generators.py
publicdata/census/files/metafiles.py
publicdata/census/files/url_templates.py
publicdata/census/files/test/__init__.py
publicdata/census/files/test/test_appurls.py
publicdata/census/files/test/test_generators.py
publicdata/census/files/test/test_issues.py
publicdata/census/files/test/test_meta.py
publicdata/census/files/test/test_urls.py
publicdata/census/test/__init__.py
publicdata/census/test/test_basic.py
publicdata/chis/__init__.py
publicdata/chis/estimate.py
publicdata/chis/prepare.py
publicdata/chis/recode.py
publicdata/docs/Census.rst
publicdata/docs/Nlsy.rst
publicdata/nlsy/README.md
publicdata/nlsy/__init__.py
publicdata/nlsy/__main__.py
publicdata/nlsy/appurl.py
publicdata/nlsy/cdb.py
publicdata/nlsy/cdb_labels.py
publicdata/nlsy/h5.py
publicdata/nlsy/nlsy.py
