Metadata-Version: 1.0
Name: publicdata
Version: 0.3.9
Summary: Metatab support code for working with public datasets
Home-page: https://github.com/CivicKnowledge/publicdata
Author: Eric Busboom
Author-email: eric@busboom.org
License: MIT
Platform: UNKNOWN
